{"url":"https://web.facebook.com","cookies":[{"domain":".facebook.com","expirationDate":1755353149.984043,"hostOnly":false,"httpOnly":true,"name":"sb","path":"/","sameSite":"no_restriction","secure":true,"session":false,"storeId":"0","value":"MTiRZm8L6e8XviWE9sgFi1yy"},{"domain":".facebook.com","expirationDate":1721397955,"hostOnly":false,"httpOnly":false,"name":"wd","path":"/","sameSite":"lax","secure":true,"session":false,"storeId":"0","value":"826x599"},{"domain":".facebook.com","expirationDate":1755353141.380442,"hostOnly":false,"httpOnly":true,"name":"datr","path":"/","sameSite":"no_restriction","secure":true,"session":false,"storeId":"0","value":"MTiRZldHuGRtMmQhad0e7vqT"},{"domain":".facebook.com","expirationDate":1752329149.984133,"hostOnly":false,"httpOnly":false,"name":"c_user","path":"/","sameSite":"no_restriction","secure":true,"session":false,"storeId":"0","value":"100057068184518"},{"domain":".facebook.com","expirationDate":1752329149.984154,"hostOnly":false,"httpOnly":true,"name":"xs","path":"/","sameSite":"no_restriction","secure":true,"session":false,"storeId":"0","value":"30%3A4qOTJkIlXtVzTg%3A2%3A1720793147%3A-1%3A11827"},{"domain":".facebook.com","expirationDate":1728569150.638552,"hostOnly":false,"httpOnly":true,"name":"fr","path":"/","sameSite":"no_restriction","secure":true,"session":false,"storeId":"0","value":"0U1PKW1naJzaFNjvG.AWUtfFkX2ZuGaqtq8eou2MEyW4U.BmkTgx..AAA.0.0.BmkTg-.AWWCDBpdsl0"},{"domain":".facebook.com","hostOnly":false,"httpOnly":false,"name":"presence","path":"/","sameSite":"unspecified","secure":true,"session":true,"storeId":"0","value":"C%7B%22t3%22%3A%5B%5D%2C%22utc3%22%3A1720793155771%2C%22v%22%3A1%7D"}]}